datacleanml/__init__.py
datacleanml/main.py
datacleanml/runner.py
datacleanml-0.2.1.dist-info/METADATA
datacleanml-0.2.1.dist-info/WHEEL
datacleanml-0.2.1.dist-info/RECORD
