Metadata-Version: 2.3
Name: datacleanml
Version: 0.2.1
Summary: A package for cleaning tabular data in preparation for machine learning
Project-URL: Homepage, https://github.com/jss367/datacleanml
Project-URL: Bug Tracker, https://github.com/jss367/datacleanml/issues
Author-email: Julius Simonelli <julius.simonelli@gmail.com>
Classifier: License :: OSI Approved :: MIT License
Classifier: Operating System :: OS Independent
Classifier: Programming Language :: Python :: 3
Requires-Python: >=3.8
Requires-Dist: numpy
Requires-Dist: pandas
Requires-Dist: python-dateutil
Requires-Dist: scikit-learn
Requires-Dist: tomli
Requires-Dist: tqdm
